{
  "applications": "*",
  "changelogDate": "20230225210141",
  "dto": "mapstruct",
  "embedded": false,
  "entityTableName": "facilitator_centre_association",
  "fields": [
    {
      "fieldName": "createTimeStamp",
      "fieldType": "Instant"
    },
    {
      "fieldName": "joinDate",
      "fieldType": "Instant"
    }
  ],
  "fluentMethods": true,
  "jpaMetamodelFiltering": false,
  "name": "FacilitatorCentreAssociation",
  "pagination": "no",
  "readOnly": false,
  "relationships": [
    {
      "otherEntityName": "facilitator",
      "otherEntityRelationshipName": "centre",
      "relationshipName": "facilitator",
      "relationshipType": "many-to-one"
    },
    {
      "otherEntityName": "centre",
      "otherEntityRelationshipName": "facilitator",
      "relationshipName": "centre",
      "relationshipType": "many-to-one"
    }
  ],
  "service": "serviceImpl"
}
